Workbook

Sheet Guide
A1: Finance models starter
A3: Sheets and the prompt each implements
A4: Yellow cells | B4: Inputs. Everything else is a formula; sample numbers are illustrative.
A5: Orders / Customers | B5: Prompt 1: fetch a customer name by sales order (INDEX and MATCH; XLOOKUP also works in current Excel).
A6: CAGR | B6: Prompt 2: compound annual growth rate from a revenue range.
A7: Scenarios | B7: Prompt 4: three scenarios from an assumptions block, with a comparison chart.
A8: DCF | B8: Prompt 6: inputs, projection, terminal value, enterprise value.
A9: Profitability | B9: Prompt 8: assumptions drive revenue, COGS, gross profit, operating expenses and net profit (before tax and interest).
A10: Anomaly | B10: Prompt 7: flag transactions more than X standard deviations from the mean.
A11: Forecast | B11: Prompt 9: linear forecast of the next 6 months with a chart.
A12: Check | B12: A model that calculates is not a model that is right: review every assumption and formula before sharing.

Sheet Orders
A1: Orders
A2: Column C fetches the customer name from the Customers sheet using the sales order as key.
A4: Sales order | B4: Order amount | C4: Customer (lookup)
A5: SO-1001 | B5: 1200 | C5: =IFERROR(INDEX(Customers!$B$5:$B$9,MATCH(A5,Customers!$A$5:$A$9,0)),"not found")
A6: SO-1002 | B6: 450 | C6: =IFERROR(INDEX(Customers!$B$5:$B$9,MATCH(A6,Customers!$A$5:$A$9,0)),"not found")
A7: SO-1003 | B7: 980 | C7: =IFERROR(INDEX(Customers!$B$5:$B$9,MATCH(A7,Customers!$A$5:$A$9,0)),"not found")
A8: SO-1004 | B8: 75 | C8: =IFERROR(INDEX(Customers!$B$5:$B$9,MATCH(A8,Customers!$A$5:$A$9,0)),"not found")
A9: SO-9999 | B9: 300 | C9: =IFERROR(INDEX(Customers!$B$5:$B$9,MATCH(A9,Customers!$A$5:$A$9,0)),"not found")

Sheet Customers
A1: Customers
A2: Sales orders with customer names and dates.
A4: Sales order | B4: Customer | C4: Date
A5: SO-1001 | B5: Alder Ltd | C5: 2026-01-12
A6: SO-1002 | B6: Birch SA | C6: 2026-01-19
A7: SO-1003 | B7: Cedar GmbH | C7: 2026-02-02
A8: SO-1004 | B8: Alder Ltd | C8: 2026-02-09
A9: SO-1005 | B9: Elm BV | C9: 2026-02-16

Sheet CAGR
A1: CAGR
A2: Annual revenue in column B; CAGR = (last / first) ^ (1 / years) - 1.
A4: Year | B4: Revenue
A5: 2022 | B5: 400000
A6: 2023 | B6: 460000
A7: 2024 | B7: 515000
A8: 2025 | B8: 590000
A9: 2026 | B9: 650000
A11: Years between | B11: =A9-A5
A12: CAGR | B12: =(B9/B5)^(1/B11)-1

Sheet Scenarios
A1: Scenario planning
A2: Three products, three scenarios, 12 months. Change the yellow cells.
A4: Assumptions
A5: Product | B5: Start customers | C5: Monthly price
A6: Product A | B6: 200 | C6: 49
A7: Product B | B7: 120 | C7: 99
A8: Product C | B8: 60 | C8: 199
A10: Scenario | B10: Monthly growth | C10: Monthly churn | D10: Net monthly rate
A11: Base | B11: 0.04 | C11: 0.02 | D11: =B11-C11
A12: Upside | B12: 0.07 | C12: 0.015 | D12: =B12-C12
A13: Downside | B13: 0.02 | C13: 0.04 | D13: =B13-C13
A15: Month-0 revenue | B15: =SUMPRODUCT(B6:B8,C6:C8)
A17: Monthly revenue by scenario
A18: Month | B18: Base | C18: Upside | D18: Downside
A19: 1 | B19: =$B$15*(1+$D$11)^$A19 | C19: =$B$15*(1+$D$12)^$A19 | D19: =$B$15*(1+$D$13)^$A19
A20: 2 | B20: =$B$15*(1+$D$11)^$A20 | C20: =$B$15*(1+$D$12)^$A20 | D20: =$B$15*(1+$D$13)^$A20
A21: 3 | B21: =$B$15*(1+$D$11)^$A21 | C21: =$B$15*(1+$D$12)^$A21 | D21: =$B$15*(1+$D$13)^$A21
A22: 4 | B22: =$B$15*(1+$D$11)^$A22 | C22: =$B$15*(1+$D$12)^$A22 | D22: =$B$15*(1+$D$13)^$A22
A23: 5 | B23: =$B$15*(1+$D$11)^$A23 | C23: =$B$15*(1+$D$12)^$A23 | D23: =$B$15*(1+$D$13)^$A23
A24: 6 | B24: =$B$15*(1+$D$11)^$A24 | C24: =$B$15*(1+$D$12)^$A24 | D24: =$B$15*(1+$D$13)^$A24
A25: 7 | B25: =$B$15*(1+$D$11)^$A25 | C25: =$B$15*(1+$D$12)^$A25 | D25: =$B$15*(1+$D$13)^$A25
A26: 8 | B26: =$B$15*(1+$D$11)^$A26 | C26: =$B$15*(1+$D$12)^$A26 | D26: =$B$15*(1+$D$13)^$A26
A27: 9 | B27: =$B$15*(1+$D$11)^$A27 | C27: =$B$15*(1+$D$12)^$A27 | D27: =$B$15*(1+$D$13)^$A27
A28: 10 | B28: =$B$15*(1+$D$11)^$A28 | C28: =$B$15*(1+$D$12)^$A28 | D28: =$B$15*(1+$D$13)^$A28
A29: 11 | B29: =$B$15*(1+$D$11)^$A29 | C29: =$B$15*(1+$D$12)^$A29 | D29: =$B$15*(1+$D$13)^$A29
A30: 12 | B30: =$B$15*(1+$D$11)^$A30 | C30: =$B$15*(1+$D$12)^$A30 | D30: =$B$15*(1+$D$13)^$A30
A32: 12-month total | B32: =SUM(B19:B30) | C32: =SUM(C19:C30) | D32: =SUM(D19:D30)

Sheet DCF
A1: DCF model
A2: All assumptions are in the yellow block; the model below only reads them.
A4: Inputs
A5: Base revenue (year 0) | B5: 1000000
A6: Annual revenue growth | B6: 0.08
A7: Costs as % of revenue | B7: 0.7
A8: Tax rate | B8: 0.25
A9: Reinvestment as % of revenue | B9: 0.03
A10: WACC | B10: 0.1
A11: Terminal growth | B11: 0.02
A13: Projection
A14: Line | B14: Year 1 | C14: Year 2 | D14: Year 3 | E14: Year 4 | F14: Year 5 | G14: Notes
A15: Revenue | B15: =$B$5*(1+$B$6) | C15: =B15*(1+$B$6) | D15: =C15*(1+$B$6) | E15: =D15*(1+$B$6) | F15: =E15*(1+$B$6)
A16: Costs | B16: =B15*$B$7 | C16: =C15*$B$7 | D16: =D15*$B$7 | E16: =E15*$B$7 | F16: =F15*$B$7
A17: Operating profit | B17: =B15-B16 | C17: =C15-C16 | D17: =D15-D16 | E17: =E15-E16 | F17: =F15-F16
A18: Tax | B18: =B17*$B$8 | C18: =C17*$B$8 | D18: =D17*$B$8 | E18: =E17*$B$8 | F18: =F17*$B$8
A19: Reinvestment | B19: =B15*$B$9 | C19: =C15*$B$9 | D19: =D15*$B$9 | E19: =E15*$B$9 | F19: =F15*$B$9
A20: Free cash flow | B20: =B17-B18-B19 | C20: =C17-C18-C19 | D20: =D17-D18-D19 | E20: =E17-E18-E19 | F20: =F17-F18-F19 | G20: FCF = operating profit - tax - reinvestment
A21: Discount factor | B21: =1/(1+$B$10)^1 | C21: =1/(1+$B$10)^2 | D21: =1/(1+$B$10)^3 | E21: =1/(1+$B$10)^4 | F21: =1/(1+$B$10)^5
A22: PV of FCF | B22: =B20*B21 | C22: =C20*C21 | D22: =D20*D21 | E22: =E20*E21 | F22: =F20*F21
A24: Sum of PV of FCF | B24: =SUM(B22:F22)
A25: Terminal value (year 5) | B25: =F20*(1+B11)/(B10-B11)
A26: PV of terminal value | B26: =B25*F21
A27: Enterprise value | B27: =B24+B26

Sheet Profitability
A1: Profitability projection
A2: Net profit here is gross profit minus operating expenses (before tax and interest).
A4: Assumptions
A5: Year 1 revenue | B5: 500000
A6: Annual revenue growth rate | B6: 0.12
A7: COGS as % of revenue | B7: 0.55
A8: Fixed operating expenses per year | B8: 90000
A11: Line | B11: Year 1 | C11: Year 2 | D11: Year 3 | E11: Year 4 | F11: Year 5
A12: Revenue | B12: =$B$5 | C12: =B12*(1+$B$6) | D12: =C12*(1+$B$6) | E12: =D12*(1+$B$6) | F12: =E12*(1+$B$6)
A13: COGS | B13: =B12*$B$7 | C13: =C12*$B$7 | D13: =D12*$B$7 | E13: =E12*$B$7 | F13: =F12*$B$7
A14: Gross profit | B14: =B12-B13 | C14: =C12-C13 | D14: =D12-D13 | E14: =E12-E13 | F14: =F12-F13
A15: Operating expenses | B15: =$B$8 | C15: =$B$8 | D15: =$B$8 | E15: =$B$8 | F15: =$B$8
A16: Net profit | B16: =B14-B15 | C16: =C14-C15 | D16: =D14-D15 | E16: =E14-E15 | F16: =F14-F15

Sheet Anomaly
A1: Anomaly detector
A2: Flags values more than X standard deviations from the average (sample standard deviation).
A4: X (std devs) | B4: 2
A6: Transaction | B6: Amount | C6: Z-score | D6: Flag
A7: T-01 | B7: 120 | C7: =(B7-$B$29)/$B$30 | D7: =IF(ABS(C7)>$B$4,"FLAG","")
A8: T-02 | B8: 135 | C8: =(B8-$B$29)/$B$30 | D8: =IF(ABS(C8)>$B$4,"FLAG","")
A9: T-03 | B9: 128 | C9: =(B9-$B$29)/$B$30 | D9: =IF(ABS(C9)>$B$4,"FLAG","")
A10: T-04 | B10: 110 | C10: =(B10-$B$29)/$B$30 | D10: =IF(ABS(C10)>$B$4,"FLAG","")
A11: T-05 | B11: 142 | C11: =(B11-$B$29)/$B$30 | D11: =IF(ABS(C11)>$B$4,"FLAG","")
A12: T-06 | B12: 125 | C12: =(B12-$B$29)/$B$30 | D12: =IF(ABS(C12)>$B$4,"FLAG","")
A13: T-07 | B13: 131 | C13: =(B13-$B$29)/$B$30 | D13: =IF(ABS(C13)>$B$4,"FLAG","")
A14: T-08 | B14: 119 | C14: =(B14-$B$29)/$B$30 | D14: =IF(ABS(C14)>$B$4,"FLAG","")
A15: T-09 | B15: 138 | C15: =(B15-$B$29)/$B$30 | D15: =IF(ABS(C15)>$B$4,"FLAG","")
A16: T-10 | B16: 127 | C16: =(B16-$B$29)/$B$30 | D16: =IF(ABS(C16)>$B$4,"FLAG","")
A17: T-11 | B17: 900 | C17: =(B17-$B$29)/$B$30 | D17: =IF(ABS(C17)>$B$4,"FLAG","")
A18: T-12 | B18: 122 | C18: =(B18-$B$29)/$B$30 | D18: =IF(ABS(C18)>$B$4,"FLAG","")
... A26: T-20 | B26: 126 | C26: =(B26-$B$29)/$B$30 | D26: =IF(ABS(C26)>$B$4,"FLAG","")
A29: Mean | B29: =AVERAGE(B7:B26)
A30: Std dev (sample) | B30: =STDEV(B7:B26)
A31: Flagged | B31: =COUNTIF(D7:D26,"FLAG")

Sheet Forecast
A1: Forecast
A2: Linear trend (FORECAST) from 12 months of history to the next 6.
A4: Month index | B4: Actual | C4: Forecast | D4: Label | F4: Slope | G4: =SLOPE(B5:B16,A5:A16)
A5: 1 | B5: 210 | D5: history | F5: Intercept | G5: =INTERCEPT(B5:B16,A5:A16)
A6: 2 | B6: 218 | D6: history
A7: 3 | B7: 225 | D7: history
A8: 4 | B8: 231 | D8: history
A9: 5 | B9: 240 | D9: history
A10: 6 | B10: 244 | D10: history
A11: 7 | B11: 255 | D11: history
A12: 8 | B12: 262 | D12: history
A13: 9 | B13: 266 | D13: history
A14: 10 | B14: 278 | D14: history
A15: 11 | B15: 283 | D15: history
A16: 12 | B16: 291 | D16: history
A17: 13 | C17: =FORECAST(A17,$B$5:$B$16,$A$5:$A$16) | D17: forecast
A18: 14 | C18: =FORECAST(A18,$B$5:$B$16,$A$5:$A$16) | D18: forecast
A19: 15 | C19: =FORECAST(A19,$B$5:$B$16,$A$5:$A$16) | D19: forecast
A20: 16 | C20: =FORECAST(A20,$B$5:$B$16,$A$5:$A$16) | D20: forecast
A21: 17 | C21: =FORECAST(A21,$B$5:$B$16,$A$5:$A$16) | D21: forecast
A22: 18 | C22: =FORECAST(A22,$B$5:$B$16,$A$5:$A$16) | D22: forecast
