Workbook

Sheet Data
B1: Line item | C1: Jan-23 | D1: Feb-23 | E1: Mar-23 | F1: Apr-23 | G1: May-23 | H1: Jun-23
B2: Revenue | C2: 41286 | D2: 13131 | E2: 35254 | F2: 79119 | G2: 23300 | H2: 52584
B3: COGS | C3: 2327 | D3: 6490 | E3: 5587 | F3: 4631 | G3: 7148 | H3: 2462
B4: Gross Profit | C4: =C2-C3 -> 38959 | D4: =D2-D3 -> 6641 | E4: =E2-E3 -> 29667 | F4: =F2-F3 -> 74488 | G4: =G2-G3 -> 16152 | H4: =H2-H3 -> 50122
B5: OpEx | C5: 18326 | D5: 21454 | E5: 17147 | F5: 5356 | G5: 7455 | H5: 6349
B6: Net Operating Income | C6: =C4-C5 -> 20633 | D6: =D4-D5 -> -14813 | E6: =E4-E5 -> 12520 | F6: =F4-F5 -> 69132 | G6: =G4-G5 -> 8697 | H6: =H4-H5 -> 43773
B7: Net Other Income | C7: 26984 | D7: 13415 | E7: 20244 | F7: 24410 | G7: 23797 | H7: 19953
B8: Net Income | C8: =C6-C7 -> -6351 | D8: =D6-D7 -> -28228 | E8: =E6-E7 -> -7724 | F8: =F6-F7 -> 44722 | G8: =G6-G7 -> -15100 | H8: =H6-H7 -> 23820
B10: Blue = inputs from the infographic (Your CFO Guy, 2024). Black = formulas.
B11: Assumption: the graphic's Net Income equals Net Operating Income MINUS 'Net Other Income' in every month, so that row behaves as other expense; the label is as printed.

Sheet Lookups
B1: Lookup practice - change the blue cells
B3: Row label | C3: Revenue
B4: Month (text, as in Data row 1) | C4: Mar-23
B5: Row label 2 | C5: Net Income
B6: Month 2 | C6: Apr-23
B7: Yellow cells are the ones to edit. Example row values above reproduce the graphic.
B9: Function | C9: Formula | D9: Result | E9: Expected from graphic | F9: Note
B10: VLOOKUP (exact) | C10: VLOOKUP($C$3,Data!$B$1:$H$8,4,FALSE) | D10: =VLOOKUP($C$3,Data!$B$1:$H$8,4,FALSE()) -> 35254 | E10: 35,254 Revenue Mar-23 | F10: 4 = Mar-23 is the 4th column of the range. FALSE = exact match. Hard-coded column number breaks if a column is inserted.
B11: VLOOKUP (column found by MATCH) | C11: VLOOKUP($C$3,Data!$B$1:$H$8,MATCH($C$4,Data!$B$1:$H$1,0),FALSE) | D11: =VLOOKUP($C$3,Data!$B$1:$H$8,MATCH($C$4,Data!$B$1:$H$1,0),FALSE()) -> 35254 | E11: 35,254 | F11: Safer: the column index follows the header.
B12: HLOOKUP (exact) | C12: HLOOKUP($C$4,Data!$B$1:$H$8,3,FALSE) | D12: =HLOOKUP($C$4,Data!$B$1:$H$8,3,FALSE()) -> 5587 | E12: 5,587 COGS Mar-23 | F12: 3 = third row of the range (header, Revenue, COGS).
B13: INDEX / MATCH | C13: INDEX(Data!$C$2:$H$8,MATCH("Gross Profit",Data!$B$2:$B$8,0),MATCH($C$4,Data!$C$1:$H$1,0)) | D13: =INDEX(Data!$C$2:$H$8,MATCH("Gross Profit",Data!$B$2:$B$8,0),MATCH($C$4,Data!$C$1:$H$1,0)) -> 29667 | E13: 29,667 Gross Profit Mar-23 | F13: Works in every Excel version and any direction; the replacement for XLOOKUP when you must share with old versions.
B14: INDEX / MATCH (second pair) | C14: INDEX(Data!$C$2:$H$8,MATCH($C$5,Data!$B$2:$B$8,0),MATCH($C$6,Data!$C$1:$H$1,0)) | D14: =INDEX(Data!$C$2:$H$8,MATCH($C$5,Data!$B$2:$B$8,0),MATCH($C$6,Data!$C$1:$H$1,0)) -> 44722 | E14: 44,722 Net Income Apr-23 | F14: Two lookups at once: the 'nested' XLOOKUP example in the graphic.
B15: Not found handled | C15: IFERROR(VLOOKUP("Marketing",Data!$B$1:$H$8,4,FALSE),"not found") | D15: =IFERROR(VLOOKUP("Marketing",Data!$B$1:$H$8,4,FALSE()),"not found") -> not found | E15: not found | F15: Use instead of a lookup error showing in the sheet. XLOOKUP has this built in (if_not_found).
B17: XLOOKUP (Excel 365 / 2021 and Google Sheets only; typed here as text, not evaluated in this file)
B18: Gross Profit Mar-23 | C18: XLOOKUP("Mar-23",Data!C1:H1,Data!C4:H4)
B19: Net Income Apr-23 (nested) | C19: XLOOKUP("Apr-23",Data!C1:H1,XLOOKUP("Net Income",Data!B2:B8,Data!C2:H8))
B20: With default if missing | C20: XLOOKUP("Jul-23",Data!C1:H1,Data!C2:H2,"not found")
B25: Source: graphic by Josh Aharonoff, Your CFO Guy (2024). Figures re-keyed from the image; formulas written for this workbook.
