Workbook

Sheet Dashboard
A1: 5-Metric SaaS Growth Efficiency Dashboard
A2: Live board panel — edit inputs on each metric tab; this summary pulls the computed results. Formulas/bands: saas-growth-efficiency-metrics skill.
A4: Metric | B4: Value | C4: Band | D4: Review order | E4: What it means
A5: Magic Number | B5: ='Magic Number'!B10 -> 0.91803279 | C5: ='Magic Number'!B11 -> EFFICIENT | D5: 1. Efficiency gate | E5: Net New ARR ÷ prior-quarter S&M spend. <0.5 broken · 0.5-0.75 fair · >0.75 efficient.
A6: Rule of 40 | B6: ='Rule of 40'!B13 -> 0.47 | C6: ='Rule of 40'!B14 -> TARGET MET | D6: 1. Efficiency gate | E6: Growth % + FCF margin %. Target ≥40%; read the two components separately, never just the sum.
A7: Net Revenue Retention | B7: ='NRR Waterfall'!B11 -> 1.1809524 | C7: ='NRR Waterfall'!B12 -> STRONG | D7: 2. Existing-base health | E7: (Start+Expansion-Churn-Contraction)/Start. <100% shrinking · 100-110% healthy · 110-120% strong · 120%+ best-in-class.
A8: LTV:CAC — best channel | B8: ='LTVCAC by Channel'!B13&" "&TEXT('LTVCAC by Channel'!B14,"0.0")&"x" -> Referral 4.6x | C8: =IF('LTVCAC by Channel'!B14<2,"KILL ZONE",IF('LTVCAC by Channel'!B14<3,"BREAKEVEN","SCALE")) -> SCALE | D8: 3. Where growth is efficient | E8: Per-channel LTV/CAC, never blended. <2:1 kill zone · 2-3:1 breakeven · >3:1 scale.
A9: CAC Payback | B9: ='CAC Payback'!B10 -> 11 | C9: ='CAC Payback'!B11 -> EXCELLENT | D9: 4. Cash-timing check | E9: CAC ÷ (MRR/customer × gross margin). <12mo excellent · 12-18mo healthy · >18mo cash problem.
A12: Board-review order (run in this sequence, not metric-list order)
A13: 1. Magic Number + Rule of 40 first — the efficiency gate. If both are weak, fix funnel/pricing before the rest.
A14: 2. NRR next — is the existing base healthy. A strong Magic Number over shrinking NRR is new-logo growth masking churn.
A15: 3. LTV:CAC by channel — where efficient growth is actually coming from; reallocate budget accordingly.
A16: 4. CAC Payback last — the cash-timing check that ratio-based LTV:CAC can miss entirely.

Sheet Magic Number
A1: Magic Number
A2: Net New ARR (annualized) ÷ prior-quarter S&M spend. Must lag S&M by one quarter.
A4: INPUTS
A5: Net New ARR ($M, annualized) | B5: 1.68
A6: Prior-quarter S&M spend ($M) | B6: 1.83
A9: RESULT
A10: Magic Number | B10: =IF(B6=0,0,B5/B6) -> 0.91803279
A11: Band | B11: =IF(B10<0.5,"BROKEN",IF(B10<0.75,"FAIR","EFFICIENT")) -> EFFICIENT
A13: BENCHMARK BANDS
A14: Band | B14: Range | C14: Action
A15: Broken | B15: < 0.50 | C15: S&M is not converting — pause spend, fix funnel/ICP before scaling.
A16: Fair | B16: 0.50 – 0.75 | C16: Invest cautiously; dial in before adding fuel.
A17: Efficient | B17: > 0.75 | C17: Scale now — S&M is a reliable lever.
A20: Trap: must lag S&M by one quarter — this quarter's spend buys next quarter's bookings.

Sheet Rule of 40
A1: Rule of 40
A2: Revenue growth % + FCF margin %. Target: sum ≥ 40%. Read the two components separately.
A4: Period | B4: Growth % | C4: FCF Margin % | D4: Total %
A5: Oct | B5: 0.31 | C5: -0.02 | D5: =B5+C5 -> 0.29
A6: Nov | B6: 0.33 | C6: -0.02 | D6: =B6+C6 -> 0.31
A7: Dec | B7: 0.34 | C7: -0.01 | D7: =B7+C7 -> 0.33
A8: Jan | B8: 0.39 | C8: 0.005 | D8: =B8+C8 -> 0.395
A9: Feb | B9: 0.44 | C9: 0.015 | D9: =B9+C9 -> 0.455
A10: Mar (current) | B10: 0.44 | C10: 0.03 | D10: =B10+C10 -> 0.47
A12: RESULT
A13: Rule of 40 (current quarter) | B13: =D10 -> 0.47
A14: Band | B14: =IF(B13>=0.4,"TARGET MET","BELOW TARGET") -> TARGET MET

Sheet NRR Waterfall
A1: Net Revenue Retention
A2: (Starting ARR + Expansion − Churn − Contraction) ÷ Starting ARR. Present as a waterfall, never a blended %.
A4: INPUTS ($M)
A5: Starting ARR | B5: 3.15
A6: Expansion | B6: 1
A7: Churn | B7: 0.3
A8: Contraction | B8: 0.13
A10: RESULT
A11: NRR % | B11: =IF(B5=0,0,(B5+B6-B7-B8)/B5) -> 1.1809524
A12: Band | B12: =IF(B11<1,"SHRINKING",IF(B11<1.1,"HEALTHY",IF(B11<1.2,"STRONG","BEST-IN-CLASS"))) -> STRONG
A15: WATERFALL HELPER (stacked-bar technique — do not edit)
A16: Step | B16: Base (invisible) | C16: Value (visible) | D16: Ending ARR
A17: Starting | B17: 0 | C17: =B5 -> 3.15 | D17: =C17 -> 3.15
A18: Expansion | B18: =B5 -> 3.15 | C18: =B6 -> 1 | D18: =D17+C18 -> 4.15
A19: Churn | B19: =B5+B6-B7 -> 3.85 | C19: =B7 -> 0.3 | D19: =D18-C19 -> 3.85
A20: Contraction | B20: =B5+B6-B7-B8 -> 3.72 | C20: =B8 -> 0.13 | D20: =D19-C20 -> 3.72
A21: Ending | B21: 0 | C21: =B5+B6-B7-B8 -> 3.72 | D21: =D20 -> 3.72

Sheet LTVCAC by Channel
A1: LTV : CAC by Channel
A2: Never blend channels into one company-wide ratio. <2:1 kill zone · 2-3:1 breakeven · >3:1 scale.
A4: Channel | B4: CAC ($) | C4: LTV ($) | D4: Ratio | H4: Band
A5: Cold Outreach | B5: 2100 | C5: 9500 | D5: =IF(B5=0,0,C5/B5) -> 4.5238095 | H5: =IF(D5<2,"KILL ZONE",IF(D5<3,"BREAKEVEN","SCALE")) -> SCALE
A6: Google Ads | B6: 2800 | C6: 9200 | D6: =IF(B6=0,0,C6/B6) -> 3.2857143 | H6: =IF(D6<2,"KILL ZONE",IF(D6<3,"BREAKEVEN","SCALE")) -> SCALE
A7: LinkedIn Ads | B7: 5200 | C7: 11500 | D7: =IF(B7=0,0,C7/B7) -> 2.2115385 | H7: =IF(D7<2,"KILL ZONE",IF(D7<3,"BREAKEVEN","SCALE")) -> BREAKEVEN
A8: Events | B8: 6800 | C8: 12200 | D8: =IF(B8=0,0,C8/B8) -> 1.7941176 | H8: =IF(D8<2,"KILL ZONE",IF(D8<3,"BREAKEVEN","SCALE")) -> KILL ZONE
A9: Referral | B9: 1000 | C9: 4600 | D9: =IF(B9=0,0,C9/B9) -> 4.6 | H9: =IF(D9<2,"KILL ZONE",IF(D9<3,"BREAKEVEN","SCALE")) -> SCALE
A10: Inbound SEO | B10: 1300 | C10: 4500 | D10: =IF(B10=0,0,C10/B10) -> 3.4615385 | H10: =IF(D10<2,"KILL ZONE",IF(D10<3,"BREAKEVEN","SCALE")) -> SCALE
A12: BEST CHANNEL (highest ratio)
A13: Channel | B13: =INDEX(A5:A10,MATCH(MAX(D5:D10),D5:D10,0)) -> Referral
A14: Ratio | B14: =MAX(D5:D10) -> 4.6

Sheet CAC Payback
A1: CAC Payback Period
A2: CAC ÷ (MRR per customer × gross margin %). <12mo excellent · 12-18mo healthy · >18mo cash problem.
A4: INPUTS
A5: CAC ($) | B5: 9900
A6: MRR per customer ($) | B6: 1250
A7: Gross margin % | B7: 0.72
A9: RESULT
A10: Payback period (months) | B10: =IF(B6*B7=0,0,B5/(B6*B7)) -> 11
A11: Band | B11: =IF(B10<=12,"EXCELLENT",IF(B10<=18,"HEALTHY","SLOW")) -> EXCELLENT
A12: Monthly gross profit ($) | B12: =B6*B7 -> 900
A15: Month | B15: Cumulative gross profit ($)
A16: 0 | B16: =$B$12*A16-$B$5 -> -9900
A17: 1 | B17: =$B$12*A17-$B$5 -> -9000
A18: 2 | B18: =$B$12*A18-$B$5 -> -8100
A19: 3 | B19: =$B$12*A19-$B$5 -> -7200
A20: 4 | B20: =$B$12*A20-$B$5 -> -6300
A21: 5 | B21: =$B$12*A21-$B$5 -> -5400
A22: 6 | B22: =$B$12*A22-$B$5 -> -4500
A23: 7 | B23: =$B$12*A23-$B$5 -> -3600
A24: 8 | B24: =$B$12*A24-$B$5 -> -2700
A25: 9 | B25: =$B$12*A25-$B$5 -> -1800
A26: 10 | B26: =$B$12*A26-$B$5 -> -900
A27: 11 | B27: =$B$12*A27-$B$5 -> 0
... A52: 36 | B52: =$B$12*A52-$B$5 -> 22500
